world_weather_report-0.4.0.dist-info/dependency_links.txt
world_weather_report-0.4.0.dist-info/entry_points.txt
world_weather_report-0.4.0.dist-info/METADATA
world_weather_report-0.4.0.dist-info/top_level.txt
world_weather_report-0.4.0.dist-info/WHEEL
world_weather_report/__init__.py
world_weather_report/cli.py
world_weather_report/utils.py
world_weather_report-0.4.0.dist-info/RECORD