Metadata-Version: 2.1
Name: world-weather-report
Version: 0.4.0
Summary: A sample Python project using dephell
Author: The Python Packaging Authority
Author-email: mgorav@gmail.com
Classifier: Programming Language :: Python :: 3.7
Classifier: License :: OSI Approved :: MIT License
Classifier: Operating System :: OS Independent
